Metadata-Version: 2.1
Name: flask-serverless
Version: 0.1.4
Summary: AWS Lambda easy integration with Flask web framework.
Home-page: https://github.com/revmischa/flask-serverless
Author: Mischa Spiegelmock
Author-email: mischa@mvstg.biz
License: WTFPL
Platform: any
Classifier: License :: OSI Approved
Classifier: Framework :: Flask
Classifier: Programming Language :: Python
Classifier: Environment :: Web Environment
Classifier: Intended Audience :: Developers
Classifier: Operating System :: OS Independent
Classifier: Topic :: Internet :: WWW/HTTP :: Dynamic Content
Classifier: Topic :: Software Development :: Libraries :: Python Modules
